elwaspatid/__init__.py
elwaspatid/elwaspatid.py
elwaspatid/prop1D_old.py
elwaspatid/prop1D_oldd.py
elwaspatid-2.0.0.dist-info/LICENSE
elwaspatid-2.0.0.dist-info/METADATA
elwaspatid-2.0.0.dist-info/WHEEL
elwaspatid-2.0.0.dist-info/top_level.txt
elwaspatid-2.0.0.dist-info/RECORD
