Metadata-Version: 2.1
Name: elwaspatid
Version: 2.0.0
Summary: Space-time diagrams for the propagation of elastic waves in 1D rods.
Home-page: https://github.com/dbrizard/ELWA-SPATID
Author: Denis Brizard
Author-email: denis.brizard@univ-eiffel.fr
License: UNKNOWN
Project-URL: Documentation, https://elwaspatid.readthedocs.io
Keywords: wave propagation,elastic wave,SHPB,rod,1D,traction,compression
Platform: UNKNOWN
Classifier: Programming Language :: Python :: 3
Classifier: License :: OSI Approved :: MIT License
Classifier: Operating System :: OS Independent
Classifier: Intended Audience :: Education
Classifier: Intended Audience :: Science/Research
Classifier: Topic :: Scientific/Engineering
Classifier: Topic :: Scientific/Engineering :: Physics
Requires-Python: >=3.6
License-File: LICENSE
